streamlit_d3_demo/__init__.py
streamlit_d3_demo/frontend/build/asset-manifest.json
streamlit_d3_demo/frontend/build/index.html
streamlit_d3_demo/frontend/build/precache-manifest.afe614a55c3b8963fcce88eb52ee73a8.js
streamlit_d3_demo/frontend/build/service-worker.js
streamlit_d3_demo/frontend/build/static/css/main.cb52735b.chunk.css
streamlit_d3_demo/frontend/build/static/css/main.cb52735b.chunk.css.map
streamlit_d3_demo/frontend/build/static/js/2.df5413bd.chunk.js
streamlit_d3_demo/frontend/build/static/js/2.df5413bd.chunk.js.LICENSE.txt
streamlit_d3_demo/frontend/build/static/js/2.df5413bd.chunk.js.map
streamlit_d3_demo/frontend/build/static/js/main.814509a9.chunk.js
streamlit_d3_demo/frontend/build/static/js/main.814509a9.chunk.js.LICENSE.txt
streamlit_d3_demo/frontend/build/static/js/main.814509a9.chunk.js.map
streamlit_d3_demo/frontend/build/static/js/runtime-main.96a7ae2f.js
streamlit_d3_demo/frontend/build/static/js/runtime-main.96a7ae2f.js.map
streamlit_d3_demo-0.1.0.dist-info/LICENSE
streamlit_d3_demo-0.1.0.dist-info/METADATA
streamlit_d3_demo-0.1.0.dist-info/WHEEL
streamlit_d3_demo-0.1.0.dist-info/top_level.txt
streamlit_d3_demo-0.1.0.dist-info/RECORD
