Metadata-Version: 2.1
Name: streamlit-d3-demo
Version: 0.1.0
Summary: Testing D3 in React hooks in Streamlit
Home-page: https://github.com/andfanilo/streamlit-d3-demo
Author: Fanilo ANDRIANASOLO
Author-email: andfanilo@gmail.com
License: UNKNOWN
Platform: UNKNOWN
Requires-Python: >=3.6
